{"stats":{"minecraft:broken":{"minecraft:iron_shovel":4,"minecraft:stone_pickaxe":2,"minecraft:golden_sword":1,"minecraft:diamond_pickaxe":1,"minecraft:stone_axe":4,"minecraft:wooden_axe":1,"minecraft:diamond_axe":1,"minecraft:iron_axe":1,"minecraft:iron_pickaxe":1},"minecraft:picked_up":{"minecraft:iron_chestplate":2,"minecraft:wheat":20,"minecraft:lead":20,"minecraft:oak_stairs":4,"minecraft:brewing_stand":1,"minecraft:string":7,"minecraft:raw_copper":47,"minecraft:iron_leggings":2,"minecraft:gold_nugget":162,"minecraft:cobbled_deepslate":334,"minecraft:spruce_planks":117,"minecraft:rose_bush":25,"minecraft:azalea":5,"minecraft:furnace":9,"minecraft:golden_helmet":2,"minecraft:stick":77,"minecraft:composter":1,"minecraft:big_dripleaf":8,"minecraft:oak_fence":2,"minecraft:torch":37,"minecraft:spruce_stairs":10,"minecraft:porkchop":35,"minecraft:rabbit_foot":1,"minecraft:rotten_flesh":7,"minecraft:obsidian":22,"minecraft:cobblestone":807,"minecraft:birch_log":15,"minecraft:enchanting_table":2,"minecraft:feather":2,"minecraft:andesite":74,"minecraft:potato":105,"minecraft:flint":6,"minecraft:tuff":16,"minecraft:lapis_lazuli":54,"minecraft:dirt":1578,"minecraft:bone":15,"minecraft:stonecutter":1,"minecraft:bow":2,"minecraft:wheat_seeds":39,"minecraft:raw_gold":21,"minecraft:bell":1,"minecraft:glowstone_dust":106,"minecraft:moss_block":4,"minecraft:oak_planks":31,"minecraft:cooked_porkchop":37,"minecraft:warped_wart_block":1,"minecraft:poisonous_potato":1,"minecraft:sand":218,"minecraft:stripped_spruce_log":36,"minecraft:lily_of_the_valley":8,"minecraft:mossy_cobblestone":214,"minecraft:diamond":32,"minecraft:spruce_boat":11,"minecraft:granite":19,"minecraft:spruce_sign":2,"minecraft:rooted_dirt":1,"minecraft:oak_sapling":7,"minecraft:netherrack":197,"minecraft:diamond_pickaxe":1,"minecraft:charcoal":4,"minecraft:coarse_dirt":206,"minecraft:crafting_table":6,"minecraft:chicken":1,"minecraft:clay_ball":24,"minecraft:brown_mushroom":57,"minecraft:gold_block":4,"minecraft:shield":2,"minecraft:moss_carpet":1,"minecraft:beef":6,"minecraft:oak_boat":4,"minecraft:poppy":4,"minecraft:spruce_slab":3,"minecraft:sugar_cane":223,"minecraft:chest":1,"minecraft:spruce_trapdoor":31,"minecraft:egg":3,"minecraft:raw_iron":47,"minecraft:oak_door":1,"minecraft:spruce_fence":8,"minecraft:redstone":31,"minecraft:arrow":8,"minecraft:nether_bricks":10,"minecraft:hay_block":21,"minecraft:glow_berries":12,"minecraft:mutton":7,"minecraft:bone_block":36,"minecraft:white_wool":7,"minecraft:basalt":2,"minecraft:glow_ink_sac":2,"minecraft:salmon":15,"minecraft:leather":7,"minecraft:red_mushroom":2,"minecraft:birch_planks":12,"minecraft:oak_log":200,"minecraft:gunpowder":3,"minecraft:cobblestone_wall":19,"minecraft:cobblestone_stairs":15,"minecraft:cooked_mutton":4,"minecraft:apple":2,"minecraft:stone_bricks":12,"minecraft:warped_stem":9,"minecraft:rabbit_hide":1,"minecraft:iron_ingot":14,"minecraft:soul_sand":13,"minecraft:flowering_azalea":17,"minecraft:book":3,"minecraft:sweet_berries":113,"minecraft:quartz":239,"minecraft:dandelion":1,"minecraft:gravel":68,"minecraft:spruce_sapling":66,"minecraft:blast_furnace":1,"minecraft:white_bed":10,"minecraft:spruce_log":1336,"minecraft:spruce_door":5,"minecraft:purple_bed":5,"minecraft:diamond_axe":1,"minecraft:warped_roots":2,"minecraft:baked_potato":6,"minecraft:coal":153,"minecraft:ender_pearl":5},"minecraft:used":{"minecraft:iron_shovel":1007,"minecraft:spruce_slab":5,"minecraft:poppy":2,"minecraft:chest":5,"minecraft:shield":18,"minecraft:bell":1,"minecraft:rotten_flesh":1,"minecraft:iron_chestplate":1,"minecraft:nether_bricks":10,"minecraft:axolotl_bucket":12,"minecraft:stripped_spruce_log":36,"minecraft:big_dripleaf":8,"minecraft:spruce_boat":11,"minecraft:stone_bricks":252,"minecraft:golden_sword":32,"minecraft:hay_block":3,"minecraft:sweet_berries":89,"minecraft:oak_sapling":5,"minecraft:furnace":13,"minecraft:gold_block":2,"minecraft:egg":1,"minecraft:potato":59,"minecraft:spruce_door":1,"minecraft:stone_pickaxe":268,"minecraft:oak_planks":383,"minecraft:ender_pearl":3,"minecraft:wooden_pickaxe":23,"minecraft:diamond_axe":1617,"minecraft:sugar_cane":19,"minecraft:white_wool":2,"minecraft:sand":26,"minecraft:bread":11,"minecraft:golden_helmet":1,"minecraft:oak_boat":5,"minecraft:coarse_dirt":65,"minecraft:bone_meal":36,"minecraft:azalea":3,"minecraft:enchanting_table":3,"minecraft:spruce_planks":110,"minecraft:stone_hoe":97,"minecraft:cooked_chicken":1,"minecraft:netherrack":70,"minecraft:oak_door":3,"minecraft:torch":36,"minecraft:dirt":1531,"minecraft:warped_wart_block":1,"minecraft:spruce_stairs":31,"minecraft:wooden_axe":49,"minecraft:flowering_azalea":3,"minecraft:bookshelf":1,"minecraft:oak_stairs":39,"minecraft:iron_axe":230,"minecraft:basalt":2,"minecraft:glowstone":24,"minecraft:cobbled_deepslate":4,"minecraft:iron_leggings":1,"minecraft:wheat_seeds":23,"minecraft:cooked_mutton":7,"minecraft:water_bucket":29,"minecraft:baked_potato":6,"minecraft:warped_roots":1,"minecraft:mossy_cobblestone":2,"minecraft:crafting_table":15,"minecraft:white_bed":8,"minecraft:spruce_log":324,"minecraft:oak_log":8,"minecraft:diamond_pickaxe":1579,"minecraft:apple":2,"minecraft:diamond_shovel":1048,"minecraft:iron_pickaxe":259,"minecraft:spruce_sapling":12,"minecraft:stone_axe":497,"minecraft:cobblestone":14,"minecraft:purple_bed":5,"minecraft:cooked_porkchop":33,"minecraft:porkchop":1,"minecraft:bucket":44,"minecraft:dandelion":1},"minecraft:killed":{"minecraft:spider":3,"minecraft:skeleton":15,"minecraft:chicken":1,"minecraft:pig":19,"minecraft:salmon":14,"minecraft:iron_golem":3,"minecraft:creeper":2,"minecraft:sheep":5,"minecraft:trader_llama":2,"minecraft:zombie":12,"minecraft:cow":2,"minecraft:drowned":8,"minecraft:wandering_trader":1,"minecraft:hoglin":1,"minecraft:enderman":2},"minecraft:custom":{"minecraft:animals_bred":5,"minecraft:interact_with_crafting_table":56,"minecraft:open_barrel":9,"minecraft:bell_ring":24,"minecraft:leave_game":10,"minecraft:time_since_death":223655,"minecraft:sprint_one_cm":745499,"minecraft:damage_blocked_by_shield":691,"minecraft:drop":71,"minecraft:talked_to_villager":17,"minecraft:play_time":604734,"minecraft:deaths":3,"minecraft:jump":7249,"minecraft:walk_on_water_one_cm":95703,"minecraft:enchant_item":3,"minecraft:interact_with_furnace":72,"minecraft:sleep_in_bed":33,"minecraft:damage_dealt":16116,"minecraft:crouch_one_cm":55791,"minecraft:interact_with_smoker":2,"minecraft:mob_kills":93,"minecraft:climb_one_cm":2485,"minecraft:walk_one_cm":1827557,"minecraft:sneak_time":23976,"minecraft:walk_under_water_one_cm":54179,"minecraft:boat_one_cm":181957,"minecraft:interact_with_blast_furnace":8,"minecraft:total_world_time":604734,"minecraft:time_since_rest":5506,"minecraft:damage_taken":4200,"minecraft:swim_one_cm":153063,"minecraft:fly_one_cm":1432398,"minecraft:open_chest":184,"minecraft:fall_one_cm":99612},"minecraft:dropped":{"minecraft:ender_pearl":2,"minecraft:diamond":11,"minecraft:cooked_porkchop":2,"minecraft:warped_roots":1,"minecraft:rooted_dirt":1,"minecraft:leather":7,"minecraft:dirt":6,"minecraft:axolotl_bucket":1,"minecraft:gold_ingot":6,"minecraft:oak_door":1,"minecraft:cobbled_deepslate":174,"minecraft:wheat":2,"minecraft:rotten_flesh":1,"minecraft:oak_planks":5,"minecraft:salmon":1,"minecraft:poppy":2,"minecraft:gunpowder":2,"minecraft:spruce_slab":13,"minecraft:wheat_seeds":7,"minecraft:cobblestone":2,"minecraft:book":1,"minecraft:spruce_door":1,"minecraft:coal":32,"minecraft:stick":5,"minecraft:spruce_sapling":12,"minecraft:sweet_berries":6,"minecraft:blast_furnace":1,"minecraft:potato":33,"minecraft:spruce_boat":2,"minecraft:spruce_trapdoor":22,"minecraft:spruce_planks":225,"minecraft:diamond_pickaxe":1,"minecraft:spruce_log":14},"minecraft:crafted":{"minecraft:oak_planks":544,"minecraft:quartz_bricks":24,"minecraft:cooked_chicken":1,"minecraft:stone":276,"minecraft:diamond_shovel":1,"minecraft:bookshelf":1,"minecraft:cooked_mutton":5,"minecraft:quartz_block":26,"minecraft:chest":4,"minecraft:stone_hoe":1,"minecraft:stone_bricks":276,"minecraft:oak_slab":6,"minecraft:cooked_porkchop":15,"minecraft:diamond_axe":2,"minecraft:crafting_table":10,"minecraft:spruce_planks":396,"minecraft:wooden_pickaxe":1,"minecraft:birch_planks":28,"minecraft:diamond_pickaxe":3,"minecraft:shield":1,"minecraft:stick":36,"minecraft:iron_ingot":20,"minecraft:iron_pickaxe":1,"minecraft:gold_ingot":21,"minecraft:oak_door":3,"minecraft:furnace":6,"minecraft:bone_meal":36,"minecraft:spruce_stairs":32,"minecraft:iron_axe":1,"minecraft:stone_pickaxe":2,"minecraft:spruce_boat":2,"minecraft:golden_helmet":1,"minecraft:wheat":9,"minecraft:cooked_beef":4,"minecraft:bucket":3,"minecraft:stone_axe":4,"minecraft:glowstone":26,"minecraft:bread":1,"minecraft:air":0,"minecraft:oak_boat":2,"minecraft:oak_stairs":40,"minecraft:wooden_axe":1,"minecraft:iron_shovel":4,"minecraft:white_bed":1,"minecraft:torch":4},"minecraft:mined":{"minecraft:spruce_planks":117,"minecraft:white_bed":8,"minecraft:farmland":50,"minecraft:cobblestone_stairs":16,"minecraft:brewing_stand":1,"minecraft:granite":19,"minecraft:obsidian":20,"minecraft:spruce_trapdoor":34,"minecraft:cave_vines_plant":3,"minecraft:grass_block":549,"minecraft:composter":1,"minecraft:glowstone":34,"minecraft:iron_ore":33,"minecraft:fire":1,"minecraft:moss_carpet":1,"minecraft:deepslate_lapis_ore":4,"minecraft:enchanting_table":2,"minecraft:cave_vines":2,"minecraft:dirt_path":102,"minecraft:flowering_azalea_leaves":3,"minecraft:oak_stairs":4,"minecraft:azalea_leaves":25,"minecraft:azalea":1,"minecraft:spruce_slab":3,"minecraft:brown_mushroom":20,"minecraft:clay":8,"minecraft:torch":7,"minecraft:chest":1,"minecraft:dead_bush":3,"minecraft:spruce_wall_sign":1,"minecraft:nether_quartz_ore":108,"minecraft:cobblestone":281,"minecraft:oak_planks":26,"minecraft:sugar_cane":87,"minecraft:seagrass":2,"minecraft:warped_nylium":1,"minecraft:birch_log":15,"minecraft:wheat":8,"minecraft:oak_log":202,"minecraft:sand":221,"minecraft:dirt":657,"minecraft:stonecutter":1,"minecraft:netherrack":159,"minecraft:oak_leaves":16,"minecraft:deepslate":248,"minecraft:nether_gold_ore":15,"minecraft:tuff":16,"minecraft:mossy_cobblestone":222,"minecraft:deepslate_diamond_ore":32,"minecraft:nether_bricks":10,"minecraft:spruce_fence":8,"minecraft:spruce_leaves":186,"minecraft:red_mushroom":2,"minecraft:moss_block":6,"minecraft:rooted_dirt":1,"minecraft:large_fern":36,"minecraft:hay_block":21,"minecraft:redstone_ore":7,"minecraft:furnace":9,"minecraft:andesite":73,"minecraft:stripped_spruce_log":36,"minecraft:gold_block":4,"minecraft:bell":1,"minecraft:bookshelf":1,"minecraft:potatoes":36,"minecraft:deepslate_iron_ore":14,"minecraft:warped_stem":9,"minecraft:stone":526,"minecraft:bone_block":36,"minecraft:white_wool":2,"minecraft:podzol":267,"minecraft:flowering_azalea":16,"minecraft:glass_pane":13,"minecraft:soul_sand":3,"minecraft:lily_of_the_valley":10,"minecraft:basalt":2,"minecraft:spruce_door":2,"minecraft:oak_fence":2,"minecraft:crafting_table":6,"minecraft:short_grass":55,"minecraft:rose_bush":25,"minecraft:tall_grass":12,"minecraft:copper_ore":12,"minecraft:lapis_ore":6,"minecraft:deepslate_gold_ore":21,"minecraft:big_dripleaf":1,"minecraft:warped_wart_block":1,"minecraft:spruce_stairs":10,"minecraft:purple_bed":5,"minecraft:coarse_dirt":204,"minecraft:cobblestone_wall":19,"minecraft:sweet_berry_bush":8,"minecraft:spruce_log":1364,"minecraft:coal_ore":109,"minecraft:gravel":78,"minecraft:stone_bricks":12,"minecraft:fern":46},"minecraft:killed_by":{"minecraft:ghast":1,"minecraft:drowned":1}},"DataVersion":3700}